pyOptimalEstimation/__init__.py
pyOptimalEstimation/pyOEcore.py
pyOptimalEstimation-1.3.dist-info/LICENSE.txt
pyOptimalEstimation-1.3.dist-info/METADATA
pyOptimalEstimation-1.3.dist-info/WHEEL
pyOptimalEstimation-1.3.dist-info/top_level.txt
pyOptimalEstimation-1.3.dist-info/RECORD
