Metadata-Version: 2.1
Name: pyOptimalEstimation
Version: 1.3
Home-page: https://github.com/maahn/pyOptimalEstimation
Author: Maximilian Maahn
License: GNU General Public License 3
Classifier: Development Status :: 5 - Production/Stable
Classifier: License :: OSI Approved :: GNU General Public License v3 (GPLv3)
Classifier: Operating System :: OS Independent
Classifier: Programming Language :: Python :: 3
Classifier: Intended Audience :: Science/Research
Classifier: Topic :: Scientific/Engineering
License-File: LICENSE.txt
Requires-Dist: numpy
Requires-Dist: matplotlib
Requires-Dist: pandas
Requires-Dist: scipy
Requires-Dist: importlib-metadata
